ally_ai_langchain/EmbeddingModel.py
ally_ai_langchain/LLM.py
ally_ai_langchain/__init__.py
ally_ai_langchain-0.5.0.dist-info/LICENSE
ally_ai_langchain-0.5.0.dist-info/METADATA
ally_ai_langchain-0.5.0.dist-info/WHEEL
ally_ai_langchain-0.5.0.dist-info/top_level.txt
ally_ai_langchain-0.5.0.dist-info/RECORD
