Metadata-Version: 2.1
Name: ally-ai-langchain
Version: 0.5.0
Summary: langchain-openai package for ally
Author-email: Tugbay Atilla <tugbayatilla@gmail.com>
Project-URL: Homepage, https://github.com/users/tugbayatilla/projects/3/
Project-URL: Issues, https://github.com/users/tugbayatilla/projects/3/views/8
Project-URL: Repository, https://github.com/tugbayatilla/ally_ai.git
Classifier: Programming Language :: Python :: 3
Classifier: License :: OSI Approved :: MIT License
Classifier: Operating System :: OS Independent
Requires-Python: >=3.8
License-File: LICENSE
Requires-Dist: ally-ai-core ~=0.5.0
Requires-Dist: langchain-openai
